{
  "billId": "119-hr-1228",
  "congress": 119,
  "type": "HR",
  "number": "1228",
  "title": "Prioritizing Veterans’ Survivors Act",
  "summary": "<p><strong>Prioritizing Veterans' Survivors Act&nbsp;</strong></p><p>This bill provides that the Office of Survivors Assistance (OSA) must operate within the Office of the Secretary of the Department of Veterans Affairs. (Currently, OSA operates within the Pension and Fiduciary Service of the Veterans Benefits Administration.)</p>",
  "latestAction": {
    "actionDate": "2025-04-10",
    "text": "Received in the Senate and Read twice and referred to the Committee on Veterans' Affairs."
  },
  "subjects": [
    "Department of Veterans Affairs",
    "Executive agency funding and structure",
    "Veterans' pensions and compensation"
  ],
  "cosponsors": 1,
  "url": "https://www.congress.gov/bill/119th-congress/house-bill/1228"
}