{
  "billId": "119-hr-5763",
  "congress": 119,
  "type": "HR",
  "number": "5763",
  "title": "Main Street Parity Act",
  "summary": "<p><strong>Main Street Parity Act</strong></p><p>This bill lessens the financing requirements for certain Small Business&nbsp;Administration loans to small businesses for plant acquisition, construction, conversion, or expansion, including the acquisition of land.&nbsp;Specifically, the bill reduces the amount of equity a borrower must provide&nbsp;by 5% of the total cost for loans for limited or single-purpose properties.</p>",
  "latestAction": {
    "actionDate": "2026-01-26",
    "text": "Received in the Senate and Read twice and referred to the Committee on Small Business and Entrepreneurship."
  },
  "subjects": [
    "Building construction",
    "Economic development",
    "Government lending and loan guarantees",
    "Small business"
  ],
  "cosponsors": 4,
  "url": "https://www.congress.gov/bill/119th-congress/house-bill/5763"
}